slothpy/__init__.py
slothpy/exporting.py
slothpy/requirements.txt
slothpy/_angular_momentum/__init__.py
slothpy/_angular_momentum/_pseudo_spin_ito.py
slothpy/_angular_momentum/_rotation.py
slothpy/_general_utilities/__init__.py
slothpy/_general_utilities/_auto_tune.py
slothpy/_general_utilities/_constants.py
slothpy/_general_utilities/_grids_over_hemisphere.py
slothpy/_general_utilities/_grids_over_sphere.py
slothpy/_general_utilities/_io.py
slothpy/_general_utilities/_math_expresions.py
slothpy/_general_utilities/_ploting_utilities.py
slothpy/_general_utilities/_system.py
slothpy/_magnetism/__init__.py
slothpy/_magnetism/_g_tensor.py
slothpy/_magnetism/_magnetisation.py
slothpy/_magnetism/_susceptibility.py
slothpy/_magnetism/_zeeman.py
slothpy/core/__init__.py
slothpy/core/_slothpy_exceptions.py
slothpy/core/compound_object.py
slothpy/core/creation_functions.py
slothpy/static/slothpy_3.png
slothpy-0.2.1.dist-info/METADATA
slothpy-0.2.1.dist-info/WHEEL
slothpy-0.2.1.dist-info/licenses/LICENSE.txt
slothpy-0.2.1.dist-info/RECORD
