Metadata-Version: 2.3
Name: slothpy
Version: 0.2.1
Summary: A small molecular magnetism related package.
Project-URL: Homepage, https://github.com/MTZ-dev/SlothPy
Project-URL: Bug Tracker, https://github.com/MTZ-dev/SlothPy/issues
Author-email: Mikolaj Tadeusz Zychowicz <mikolaj.zychowicz@uj.edu.pl>
License:                     GNU GENERAL PUBLIC LICENSE
License-File: LICENSE.txt
Classifier: License :: OSI Approved :: GNU General Public License v3 (GPLv3)
Classifier: Operating System :: OS Independent
Classifier: Programming Language :: Python :: 3
Requires-Python: >=3.10
Requires-Dist: cycler>=0.11.0
Requires-Dist: docx>=0.2.4
Requires-Dist: h5py>=3.8.0
Requires-Dist: ipython>=8.13.2
Requires-Dist: matplotlib>=3.7.1
Requires-Dist: numba>=0.57.0
Requires-Dist: numpy>=1.24.3
Requires-Dist: pandas>=2.0.1
Requires-Dist: pyqt5>=5.15.9
Requires-Dist: python-docx>=1.0.1
Requires-Dist: scipy>=1.11.2
Requires-Dist: threadpoolctl>=3.2.0
